{
    "image": "15.png",
    "dimensions": {
        "width": 2481,
        "height": 3508
    },
    "table_found": true,
    "cells": [
        {
            "type": "header",
            "box": [
                118,
                287,
                2361,
                2182
            ]
        },
        {
            "type": "header",
            "box": [
                119,
                288,
                1396,
                348
            ]
        },
        {
            "type": "header",
            "box": [
                1396,
                288,
                2359,
                348
            ]
        },
        {
            "type": "cell",
            "box": [
                119,
                349,
                1396,
                413
            ]
        },
        {
            "type": "cell",
            "box": [
                1396,
                349,
                2359,
                413
            ]
        },
        {
            "type": "cell",
            "box": [
                119,
                414,
                1396,
                478
            ]
        },
        {
            "type": "cell",
            "box": [
                1396,
                414,
                2359,
                478
            ]
        },
        {
            "type": "cell",
            "box": [
                119,
                479,
                1396,
                543
            ]
        },
        {
            "type": "cell",
            "box": [
                1396,
                479,
                2359,
                543
            ]
        },
        {
            "type": "cell",
            "box": [
                119,
                544,
                1396,
                608
            ]
        },
        {
            "type": "cell",
            "box": [
                1396,
                544,
                2359,
                608
            ]
        },
        {
            "type": "cell",
            "box": [
                119,
                609,
                1396,
                673
            ]
        },
        {
            "type": "cell",
            "box": [
                1396,
                609,
                2359,
                673
            ]
        },
        {
            "type": "cell",
            "box": [
                119,
                674,
                1396,
                738
            ]
        },
        {
            "type": "cell",
            "box": [
                1396,
                674,
                2359,
                738
            ]
        },
        {
            "type": "cell",
            "box": [
                119,
                739,
                1396,
                803
            ]
        },
        {
            "type": "cell",
            "box": [
                1396,
                739,
                2359,
                803
            ]
        },
        {
            "type": "cell",
            "box": [
                119,
                804,
                1396,
                868
            ]
        },
        {
            "type": "cell",
            "box": [
                1396,
                804,
                2359,
                868
            ]
        },
        {
            "type": "cell",
            "box": [
                119,
                868,
                1396,
                933
            ]
        },
        {
            "type": "cell",
            "box": [
                1396,
                868,
                2359,
                933
            ]
        },
        {
            "type": "cell",
            "box": [
                119,
                933,
                1396,
                998
            ]
        },
        {
            "type": "cell",
            "box": [
                1396,
                933,
                2359,
                998
            ]
        },
        {
            "type": "cell",
            "box": [
                119,
                998,
                1396,
                1063
            ]
        },
        {
            "type": "cell",
            "box": [
                1396,
                998,
                2359,
                1063
            ]
        },
        {
            "type": "cell",
            "box": [
                119,
                1063,
                1396,
                1128
            ]
        },
        {
            "type": "cell",
            "box": [
                1396,
                1063,
                2359,
                1128
            ]
        },
        {
            "type": "cell",
            "box": [
                119,
                1128,
                1396,
                1193
            ]
        },
        {
            "type": "cell",
            "box": [
                1396,
                1128,
                2359,
                1193
            ]
        },
        {
            "type": "cell",
            "box": [
                119,
                1193,
                1396,
                1258
            ]
        },
        {
            "type": "cell",
            "box": [
                1396,
                1193,
                2359,
                1258
            ]
        },
        {
            "type": "cell",
            "box": [
                119,
                1258,
                1396,
                1323
            ]
        },
        {
            "type": "cell",
            "box": [
                1396,
                1258,
                2359,
                1323
            ]
        },
        {
            "type": "cell",
            "box": [
                119,
                1323,
                1396,
                1388
            ]
        },
        {
            "type": "cell",
            "box": [
                1396,
                1323,
                2359,
                1388
            ]
        },
        {
            "type": "cell",
            "box": [
                119,
                1388,
                1396,
                1497
            ]
        },
        {
            "type": "cell",
            "box": [
                1396,
                1388,
                2359,
                1497
            ]
        },
        {
            "type": "cell",
            "box": [
                119,
                1497,
                1396,
                1690
            ]
        },
        {
            "type": "cell",
            "box": [
                1396,
                1497,
                2359,
                1690
            ]
        },
        {
            "type": "cell",
            "box": [
                119,
                1690,
                1396,
                1755
            ]
        },
        {
            "type": "cell",
            "box": [
                1396,
                1690,
                2359,
                1755
            ]
        },
        {
            "type": "cell",
            "box": [
                119,
                1755,
                1396,
                1820
            ]
        },
        {
            "type": "cell",
            "box": [
                1396,
                1755,
                2359,
                1820
            ]
        },
        {
            "type": "cell",
            "box": [
                119,
                1820,
                2359,
                1856
            ]
        },
        {
            "type": "cell",
            "box": [
                119,
                1856,
                1396,
                1921
            ]
        },
        {
            "type": "cell",
            "box": [
                1396,
                1856,
                2359,
                1921
            ]
        },
        {
            "type": "cell",
            "box": [
                119,
                1921,
                1396,
                1986
            ]
        },
        {
            "type": "cell",
            "box": [
                1396,
                1921,
                2359,
                1986
            ]
        },
        {
            "type": "cell",
            "box": [
                119,
                1986,
                1396,
                2051
            ]
        },
        {
            "type": "cell",
            "box": [
                1396,
                1986,
                2359,
                2051
            ]
        },
        {
            "type": "cell",
            "box": [
                119,
                2051,
                1396,
                2116
            ]
        },
        {
            "type": "cell",
            "box": [
                1396,
                2051,
                2359,
                2116
            ]
        },
        {
            "type": "cell",
            "box": [
                119,
                2116,
                1396,
                2181
            ]
        },
        {
            "type": "cell",
            "box": [
                1396,
                2116,
                2359,
                2181
            ]
        },
        {
            "type": "cell",
            "box": [
                118,
                2461,
                2363,
                3326
            ]
        }
    ]
}